tradedoubler_api_client/__init__.py
tradedoubler_api_client/client.py
tradedoubler_api_client/exceptions.py
tradedoubler_api_client/pending_sales.py
tradedoubler_api_client/reporting.py
tradedoubler_api_client/utilities.py
tradedoubler_api_client-0.7.5.dist-info/LICENSE
tradedoubler_api_client-0.7.5.dist-info/METADATA
tradedoubler_api_client-0.7.5.dist-info/WHEEL
tradedoubler_api_client-0.7.5.dist-info/top_level.txt
tradedoubler_api_client-0.7.5.dist-info/RECORD
