Metadata-Version: 2.1
Name: tradedoubler-api-client
Version: 0.7.5
Summary: Unofficial simple python wrapper for Tradedoubler API
Home-page: https://github.com/adamczarnecki/tradedoubler_api_client
Author: Adam Czarnecki
Author-email: adam@czarnecki.cz
License: MIT
Classifier: Development Status :: 3 - Alpha
Classifier: Programming Language :: Python :: 3
Classifier: Programming Language :: Python :: 3.6
Classifier: License :: OSI Approved :: MIT License
Classifier: Operating System :: OS Independent
Requires-Python: >=3.6
License-File: LICENSE
Requires-Dist: requests
